LICENSE
MANIFEST.in
README.md
pyproject.toml
setup.py
id_marl_eval.egg-info/PKG-INFO
id_marl_eval.egg-info/SOURCES.txt
id_marl_eval.egg-info/dependency_links.txt
id_marl_eval.egg-info/requires.txt
id_marl_eval.egg-info/top_level.txt
marl_eval/__init__.py
marl_eval/_metadata.py
marl_eval/json_tools/__init__.py
marl_eval/json_tools/json_logger.py
marl_eval/json_tools/json_utils.py
marl_eval/plotting_tools/__init__.py
marl_eval/plotting_tools/plot_utils.py
marl_eval/plotting_tools/plotting.py
marl_eval/utils/__init__.py
marl_eval/utils/data_processing_utils.py
marl_eval/utils/diagnose_data_errors.py
requirements/requirements-dev.txt
requirements/requirements.txt