Metadata-Version: 2.1
Name: id-marl-eval
Version: 0.0.4
Summary: A Python library for Multi-Agent Reinforcement Learning evaluation.
Author: InstaDeep Ltd
License: Apache License, Version 2.0
Keywords: multi-agent reinforcement-learning python machine learning
Classifier: Development Status :: 3 - Alpha
Classifier: Environment :: Console
Classifier: Intended Audience :: Science/Research
Classifier: License :: OSI Approved :: Apache Software License
Classifier: Operating System :: POSIX :: Linux
Classifier: Programming Language :: Python :: 3
Classifier: Programming Language :: Python :: 3.8
Classifier: Topic :: Scientific/Engineering :: Artificial Intelligence
License-File: LICENSE
Requires-Dist: colorcet==3.0.0
Requires-Dist: matplotlib>=3.5.3
Requires-Dist: numpy
Requires-Dist: rliable
Requires-Dist: seaborn
Requires-Dist: pandas==1.4.4
Requires-Dist: Jinja2
Requires-Dist: importlib-metadata<5.0
Requires-Dist: colorama
Requires-Dist: neptune
Requires-Dist: tqdm
Provides-Extra: dev
Requires-Dist: pre-commit; extra == "dev"
Requires-Dist: mypy; extra == "dev"
Requires-Dist: flake8; extra == "dev"
Requires-Dist: black; extra == "dev"
Requires-Dist: interrogate; extra == "dev"
Requires-Dist: pydocstyle; extra == "dev"
Requires-Dist: types-six; extra == "dev"
Requires-Dist: toml; extra == "dev"
Requires-Dist: pytest==6.2.4; extra == "dev"
Requires-Dist: pytest-xdist; extra == "dev"
Requires-Dist: jax[cpu]; extra == "dev"
Requires-Dist: codespell==2.2.6; extra == "dev"
